game_machine/__init__.py
game_machine/container.py
game_machine/eventobject.py
game_machine/maths.py
game_machine/screen.py
game_machine/window.py
game_machine/sprites/__init__.py
game_machine/sprites/circle.py
game_machine/sprites/film_strip.py
game_machine/sprites/multi_sprite.py
game_machine/sprites/picture.py
game_machine/sprites/polygon.py
game_machine/sprites/rectangle.py
game_machine/sprites/sprite.py
game_machine/sprites/text.py
game_machine/sprites/vector_sprite.py
game_machine-0.5.dist-info/DESCRIPTION.rst
game_machine-0.5.dist-info/METADATA
game_machine-0.5.dist-info/RECORD
game_machine-0.5.dist-info/WHEEL
game_machine-0.5.dist-info/metadata.json
game_machine-0.5.dist-info/top_level.txt
