Metadata-Version: 2.0
Name: game-machine
Version: 0.5
Summary: A 2D sprite based game engine/PyGame wrapper
Home-page: https://github.com/thismachinekillszombies/game_machine
Author: Richard Butterworth
Author-email: richard@richardbutterworth.co.uk
License: MIT
Platform: UNKNOWN
Classifier: Programming Language :: Python
Classifier: License :: OSI Approved :: MIT License
Classifier: Natural Language :: English
Classifier: Operating System :: OS Independent
Classifier: Topic :: Education
Classifier: Topic :: Games/Entertainment
Requires-Dist: pygame
